engine/__init__.py
engine/input.py
engine/text.py
engine/theme.py
engine/util.py
engine/window.py
engine/components/__init__.py
engine/components/base.py
engine/components/button.py
engine/components/checkbox.py
engine/components/childwindow.py
engine/components/dropdown.py
engine/components/field.py
engine/components/frame.py
engine/components/iconbutton.py
engine/components/image.py
engine/components/label.py
engine/components/progress.py
engine/components/radio.py
engine/components/segmented.py
engine/components/slider.py
engine/components/tabframe.py
engine/components/toggle.py
ui_engine-7.2.0.data/data/VERSION
ui_engine-7.2.0.dist-info/licenses/COPYING.md
ui_engine-7.2.0.dist-info/METADATA
ui_engine-7.2.0.dist-info/WHEEL
ui_engine-7.2.0.dist-info/top_level.txt
ui_engine-7.2.0.dist-info/RECORD
