Metadata-Version: 2.4
Name: ui-engine
Version: 7.2.0
Summary: UI Engine
Home-page: https://github.com/Omena0/UI-Engine-V2
Author: Omena0
License: PolyForm Noncommercial 1.0.0
Classifier: Programming Language :: Python :: 3
Classifier: Programming Language :: Python :: 3.8
Classifier: Programming Language :: Python :: 3.9
Classifier: Programming Language :: Python :: 3.10
Classifier: Programming Language :: Python :: 3.11
Classifier: Programming Language :: Python :: 3.12
Classifier: Programming Language :: Python :: 3.13
Classifier: License :: Other/Proprietary License
Classifier: Operating System :: OS Independent
Classifier: Topic :: Software Development :: User Interfaces
Classifier: Topic :: Multimedia :: Graphics
Classifier: Topic :: Games/Entertainment
Requires-Python: >=3.8
License-File: COPYING.md
Requires-Dist: pygame-ce
Requires-Dist: clipboard
Dynamic: description
Dynamic: description-content-type
Dynamic: license-file
Dynamic: summary
